{
  "id": "acec7a1f-542e-425a-bad3-01360fa4b2ca",
  "prevId": "00000000-0000-0000-0000-000000000000",
  "version": "7",
  "dialect": "postgresql",
  "tables": {
    "public.answers": {
      "name": "answers",
      "schema": "",
      "columns": {
        "id": {
          "name": "id",
          "type": "serial",
          "primaryKey": true,
          "notNull": true
        },
        "interview_id": {
          "name": "interview_id",
          "type": "integer",
          "primaryKey": false,
          "notNull": true
        },
        "question_index": {
          "name": "question_index",
          "type": "integer",
          "primaryKey": false,
          "notNull": true
        },
        "question_text": {
          "name": "question_text",
          "type": "text",
          "primaryKey": false,
          "notNull": true
        },
        "answer_text": {
          "name": "answer_text",
          "type": "text",
          "primaryKey": false,
          "notNull": true
        },
        "score": {
          "name": "score",
          "type": "integer",
          "primaryKey": false,
          "notNull": true
        },
        "feedback": {
          "name": "feedback",
          "type": "text",
          "primaryKey": false,
          "notNull": true
        },
        "created_at": {
          "name": "created_at",
          "type": "timestamp",
          "primaryKey": false,
          "notNull": true,
          "default": "now()"
        }
      },
      "indexes": {},
      "foreignKeys": {
        "answers_interview_id_interviews_id_fk": {
          "name": "answers_interview_id_interviews_id_fk",
          "tableFrom": "answers",
          "tableTo": "interviews",
          "columnsFrom": [
            "interview_id"
          ],
          "columnsTo": [
            "id"
          ],
          "onDelete": "no action",
          "onUpdate": "no action"
        }
      },
      "compositePrimaryKeys": {},
      "uniqueConstraints": {},
      "policies": {},
      "checkConstraints": {},
      "isRLSEnabled": false
    },
    "public.candidates": {
      "name": "candidates",
      "schema": "",
      "columns": {
        "id": {
          "name": "id",
          "type": "serial",
          "primaryKey": true,
          "notNull": true
        },
        "name": {
          "name": "name",
          "type": "text",
          "primaryKey": false,
          "notNull": true
        },
        "email": {
          "name": "email",
          "type": "text",
          "primaryKey": false,
          "notNull": true
        },
        "phone": {
          "name": "phone",
          "type": "text",
          "primaryKey": false,
          "notNull": true
        },
        "job_role": {
          "name": "job_role",
          "type": "text",
          "primaryKey": false,
          "notNull": true
        },
        "resume_text": {
          "name": "resume_text",
          "type": "text",
          "primaryKey": false,
          "notNull": true
        },
        "created_at": {
          "name": "created_at",
          "type": "timestamp",
          "primaryKey": false,
          "notNull": true,
          "default": "now()"
        }
      },
      "indexes": {},
      "foreignKeys": {},
      "compositePrimaryKeys": {},
      "uniqueConstraints": {
        "candidates_email_unique": {
          "name": "candidates_email_unique",
          "nullsNotDistinct": false,
          "columns": [
            "email"
          ]
        }
      },
      "policies": {},
      "checkConstraints": {},
      "isRLSEnabled": false
    },
    "public.evaluations": {
      "name": "evaluations",
      "schema": "",
      "columns": {
        "id": {
          "name": "id",
          "type": "serial",
          "primaryKey": true,
          "notNull": true
        },
        "interview_id": {
          "name": "interview_id",
          "type": "integer",
          "primaryKey": false,
          "notNull": true
        },
        "overall_score": {
          "name": "overall_score",
          "type": "integer",
          "primaryKey": false,
          "notNull": true
        },
        "technical_score": {
          "name": "technical_score",
          "type": "integer",
          "primaryKey": false,
          "notNull": true
        },
        "behavioral_score": {
          "name": "behavioral_score",
          "type": "integer",
          "primaryKey": false,
          "notNull": true
        },
        "strengths": {
          "name": "strengths",
          "type": "text",
          "primaryKey": false,
          "notNull": true
        },
        "improvement_areas": {
          "name": "improvement_areas",
          "type": "text",
          "primaryKey": false,
          "notNull": true
        },
        "recommendation": {
          "name": "recommendation",
          "type": "text",
          "primaryKey": false,
          "notNull": true
        },
        "created_at": {
          "name": "created_at",
          "type": "timestamp",
          "primaryKey": false,
          "notNull": true,
          "default": "now()"
        }
      },
      "indexes": {},
      "foreignKeys": {
        "evaluations_interview_id_interviews_id_fk": {
          "name": "evaluations_interview_id_interviews_id_fk",
          "tableFrom": "evaluations",
          "tableTo": "interviews",
          "columnsFrom": [
            "interview_id"
          ],
          "columnsTo": [
            "id"
          ],
          "onDelete": "no action",
          "onUpdate": "no action"
        }
      },
      "compositePrimaryKeys": {},
      "uniqueConstraints": {},
      "policies": {},
      "checkConstraints": {},
      "isRLSEnabled": false
    },
    "public.interviews": {
      "name": "interviews",
      "schema": "",
      "columns": {
        "id": {
          "name": "id",
          "type": "serial",
          "primaryKey": true,
          "notNull": true
        },
        "candidate_id": {
          "name": "candidate_id",
          "type": "integer",
          "primaryKey": false,
          "notNull": true
        },
        "questions": {
          "name": "questions",
          "type": "jsonb",
          "primaryKey": false,
          "notNull": true
        },
        "current_question_index": {
          "name": "current_question_index",
          "type": "integer",
          "primaryKey": false,
          "notNull": true,
          "default": 0
        },
        "status": {
          "name": "status",
          "type": "text",
          "primaryKey": false,
          "notNull": true,
          "default": "'pending'"
        },
        "created_at": {
          "name": "created_at",
          "type": "timestamp",
          "primaryKey": false,
          "notNull": true,
          "default": "now()"
        },
        "completed_at": {
          "name": "completed_at",
          "type": "timestamp",
          "primaryKey": false,
          "notNull": false
        }
      },
      "indexes": {},
      "foreignKeys": {
        "interviews_candidate_id_candidates_id_fk": {
          "name": "interviews_candidate_id_candidates_id_fk",
          "tableFrom": "interviews",
          "tableTo": "candidates",
          "columnsFrom": [
            "candidate_id"
          ],
          "columnsTo": [
            "id"
          ],
          "onDelete": "no action",
          "onUpdate": "no action"
        }
      },
      "compositePrimaryKeys": {},
      "uniqueConstraints": {},
      "policies": {},
      "checkConstraints": {},
      "isRLSEnabled": false
    },
    "public.settings": {
      "name": "settings",
      "schema": "",
      "columns": {
        "id": {
          "name": "id",
          "type": "serial",
          "primaryKey": true,
          "notNull": true
        },
        "key": {
          "name": "key",
          "type": "text",
          "primaryKey": false,
          "notNull": true
        },
        "value": {
          "name": "value",
          "type": "text",
          "primaryKey": false,
          "notNull": true
        }
      },
      "indexes": {},
      "foreignKeys": {},
      "compositePrimaryKeys": {},
      "uniqueConstraints": {
        "settings_key_unique": {
          "name": "settings_key_unique",
          "nullsNotDistinct": false,
          "columns": [
            "key"
          ]
        }
      },
      "policies": {},
      "checkConstraints": {},
      "isRLSEnabled": false
    },
    "public.users": {
      "name": "users",
      "schema": "",
      "columns": {
        "id": {
          "name": "id",
          "type": "serial",
          "primaryKey": true,
          "notNull": true
        },
        "email": {
          "name": "email",
          "type": "text",
          "primaryKey": false,
          "notNull": true
        },
        "password": {
          "name": "password",
          "type": "text",
          "primaryKey": false,
          "notNull": true
        },
        "role": {
          "name": "role",
          "type": "text",
          "primaryKey": false,
          "notNull": true
        },
        "created_at": {
          "name": "created_at",
          "type": "timestamp",
          "primaryKey": false,
          "notNull": true,
          "default": "now()"
        }
      },
      "indexes": {},
      "foreignKeys": {},
      "compositePrimaryKeys": {},
      "uniqueConstraints": {
        "users_email_unique": {
          "name": "users_email_unique",
          "nullsNotDistinct": false,
          "columns": [
            "email"
          ]
        }
      },
      "policies": {},
      "checkConstraints": {},
      "isRLSEnabled": false
    }
  },
  "enums": {},
  "schemas": {},
  "sequences": {},
  "roles": {},
  "policies": {},
  "views": {},
  "_meta": {
    "columns": {},
    "schemas": {},
    "tables": {}
  }
}